binp/__init__.py
binp/action.py
binp/api.py
binp/db.py
binp/events.py
binp/journals.py
binp/kv.py
binp/service.py
binp/migrations/0001_init.sql
binp/migrations/0002_journal_label.sql
binp/static/404.svg
binp/static/favicon.ico
binp/static/favicon.png
binp/static/global.css
binp/static/index.html
binp/static/logo.svg
binp/static/main.scss
binp/static/manifest.json
binp/static/robots.txt
binp/static/serviceworker.js
binp/static/build/bundle.css
binp/static/build/main.js
binp/static/images/touch-icons/logo-192.png
binp/static/images/touch-icons/logo-800.png
binp-0.0.7.dist-info/LICENSE
binp-0.0.7.dist-info/METADATA
binp-0.0.7.dist-info/WHEEL
binp-0.0.7.dist-info/top_level.txt
binp-0.0.7.dist-info/RECORD
