Metadata-Version: 2.1
Name: binp
Version: 0.0.7
Summary: Basic Integration Platform
Home-page: https://github.com/reddec/binp
Author: Aleksandr Baryshnikov
Author-email: owner@reddec.net
License: MIT
Platform: UNKNOWN
Classifier: Programming Language :: Python :: 3.8
Classifier: License :: OSI Approved :: MIT License
Classifier: Operating System :: OS Independent
Classifier: Intended Audience :: Developers
Classifier: Intended Audience :: System Administrators
Requires-Python: >=3.8
Requires-Dist: fastapi (~=0.63.0)
Requires-Dist: aiofiles (~=0.6.0)
Requires-Dist: databases[sqlite] (~=0.4.1)
